json_cli/__init__.py
json_cli/cli.py
json_cli/json_file.py
json_cli-0.1.6.dist-info/entry_points.txt
json_cli-0.1.6.dist-info/WHEEL
json_cli-0.1.6.dist-info/METADATA
json_cli-0.1.6.dist-info/RECORD
