Metadata-Version: 2.1
Name: json-cli
Version: 0.1.6
Summary: 
Author: Eyal Levin
Author-email: eyalev@gmail.com
Requires-Python: >=3.6,<4.0
Classifier: Programming Language :: Python :: 3
Classifier: Programming Language :: Python :: 3.6
Classifier: Programming Language :: Python :: 3.7
Classifier: Programming Language :: Python :: 3.8
Requires-Dist: click (>=7.1.2,<8.0.0)
Requires-Dist: file-util (>=0.1.3,<0.2.0)
Requires-Dist: pobject (>=0.1.4,<0.2.0)
